fmmax/__init__.py
fmmax/_basis.py
fmmax/_fft.py
fmmax/_fields.py
fmmax/_fmm.py
fmmax/_fmm_result.py
fmmax/_scattering.py
fmmax/_utils.py
fmmax/basis.py
fmmax/beams.py
fmmax/eig.py
fmmax/farfield.py
fmmax/fft.py
fmmax/fields.py
fmmax/fmm.py
fmmax/fmm_matrices.py
fmmax/misc.py
fmmax/pml.py
fmmax/py.typed
fmmax/scattering.py
fmmax/sources.py
fmmax/translate.py
fmmax/utils.py
fmmax/vector.py
fmmax-1.7.1.dist-info/licenses/LICENSE
fmmax-1.7.1.dist-info/METADATA
fmmax-1.7.1.dist-info/WHEEL
fmmax-1.7.1.dist-info/top_level.txt
fmmax-1.7.1.dist-info/RECORD
