Metadata-Version: 2.4
Name: fmmax
Version: 1.7.1
Summary: Fourier modal method with Jax
Author-email: Martin Schubert <mfschubert@gmail.com>, Alec Hammond <alec.m.hammond@gmail.com>
Maintainer-email: Martin Schubert <mfschubert@gmail.com>
License-Expression: MIT
Keywords: fmm,rcwa,jax,optics
Requires-Python: >=3.10
License-File: LICENSE
Requires-Dist: jax>=0.4.36
Requires-Dist: jaxlib
Requires-Dist: numpy
Provides-Extra: docs
Requires-Dist: matplotlib; extra == "docs"
Requires-Dist: jupyter-book==1.0.4.post1; extra == "docs"
Requires-Dist: sphinx-autodoc-typehints; extra == "docs"
Requires-Dist: sphinx-click; extra == "docs"
Provides-Extra: examples
Requires-Dist: matplotlib; extra == "examples"
Requires-Dist: scikit-image; extra == "examples"
Requires-Dist: scipy; extra == "examples"
Provides-Extra: jeig
Requires-Dist: jeig; extra == "jeig"
Provides-Extra: tests
Requires-Dist: grcwa; extra == "tests"
Requires-Dist: parameterized; extra == "tests"
Requires-Dist: pytest; extra == "tests"
Requires-Dist: pytest-subtests; extra == "tests"
Provides-Extra: dev
Requires-Dist: bump-my-version; extra == "dev"
Requires-Dist: darglint; extra == "dev"
Requires-Dist: fmmax[docs,examples,tests]; extra == "dev"
Requires-Dist: isort; extra == "dev"
Requires-Dist: mypy; extra == "dev"
Requires-Dist: pre-commit; extra == "dev"
Dynamic: license-file
